pyper/__init__.py
pyper/_core/decorators.py
pyper/_core/pipeline.py
pyper/_core/task.py
pyper/_core/async_helper/output.py
pyper/_core/async_helper/queue_io.py
pyper/_core/async_helper/stage.py
pyper/_core/sync_helper/output.py
pyper/_core/sync_helper/queue_io.py
pyper/_core/sync_helper/stage.py
pyper/_core/util/asynchronize.py
pyper/_core/util/sentinel.py
pyper/_core/util/task_group.py
pyper/_core/util/worker_pool.py
python_pyper-0.4.4.dist-info/LICENSE
python_pyper-0.4.4.dist-info/METADATA
python_pyper-0.4.4.dist-info/WHEEL
python_pyper-0.4.4.dist-info/top_level.txt
python_pyper-0.4.4.dist-info/RECORD
