Metadata-Version: 2.2
Name: python-pyper
Version: 0.4.4
Summary: Concurrent Python made simple
Author-email: Richard Zhu <richard.zhu2@gmail.com>
Project-URL: Homepage, https://pyper-dev.github.io/pyper/
Project-URL: Documentation, https://pyper-dev.github.io/pyper/
Project-URL: Repository, https://github.com/pyper-dev/pyper
Project-URL: Issues, https://github.com/pyper-dev/pyper/issues
Classifier: Intended Audience :: Developers
Classifier: Operating System :: OS Independent
Classifier: Programming Language :: Python :: 3
Classifier: Programming Language :: Python
Classifier: Topic :: Software Development :: Libraries
Classifier: Topic :: Software Development
Classifier: Framework :: AsyncIO
Classifier: License :: OSI Approved :: MIT License
Classifier: Programming Language :: Python :: 3 :: Only
Classifier: Programming Language :: Python :: 3.8
Classifier: Programming Language :: Python :: 3.9
Classifier: Programming Language :: Python :: 3.10
Classifier: Programming Language :: Python :: 3.11
Classifier: Programming Language :: Python :: 3.12
Classifier: Programming Language :: Python :: 3.13
Requires-Python: >=3.8
License-File: LICENSE
Requires-Dist: typing_extensions; python_version < "3.10"
